py50/.DS_Store
py50/__init__.py
py50/calculator.py
py50/plot_settings.py
py50/plotcurve.py
py50/stats.py
py50/utils.py
py50-1.0.12.dist-info/METADATA
py50-1.0.12.dist-info/WHEEL
py50-1.0.12.dist-info/licenses/LICENSE
py50-1.0.12.dist-info/RECORD
