Metadata-Version: 2.4
Name: py50
Version: 1.0.12
Summary: Generate Dose-Response Curves
License: GPL-3.0-only
License-File: LICENSE
Author: Tony Eight Lin
Author-email: tonyelin@tmu.edu.tw
Requires-Python: >=3.9
Classifier: License :: OSI Approved :: GNU General Public License v3 (GPLv3)
Classifier: Programming Language :: Python :: 3
Classifier: Programming Language :: Python :: 3.9
Classifier: Programming Language :: Python :: 3.10
Classifier: Programming Language :: Python :: 3.11
Classifier: Programming Language :: Python :: 3.12
Classifier: Programming Language :: Python :: 3.13
Classifier: Programming Language :: Python :: 3.14
Requires-Dist: matplotlib (>=3.8.1)
Requires-Dist: numpy (>=1.26.4)
Requires-Dist: pandas (>=1.5.0)
Requires-Dist: pingouin (>=0.5.4)
Requires-Dist: scikit-posthocs (>=0.7.0)
Requires-Dist: scipy (>=1.11.3)
Requires-Dist: seaborn (>=0.12.2)
Requires-Dist: statannotations (>=0.6.0)
Project-URL: Documentation, https://py50.readthedocs.io/en/latest/
Project-URL: Repository, https://github.com/tlint101/py50.git
